custom_user/__init__.py
custom_user/admin.py
custom_user/apps.py
custom_user/forms.py
custom_user/models.py
custom_user/tests.py
custom_user/migrations/0001_initial_django17.py
custom_user/migrations/0002_initial_django18.py
custom_user/migrations/__init__.py
django_custom_user-0.7.dist-info/DESCRIPTION.rst
django_custom_user-0.7.dist-info/METADATA
django_custom_user-0.7.dist-info/RECORD
django_custom_user-0.7.dist-info/WHEEL
django_custom_user-0.7.dist-info/metadata.json
django_custom_user-0.7.dist-info/top_level.txt
