Metadata-Version: 2.0
Name: django-custom-user
Version: 0.7
Summary: Custom user model for Django >= 1.5 with the same behaviour as Django's default User but with email instead of username.
Home-page: https://github.com/jcugat/django-custom-user
Author: Josep Cugat
Author-email: jcugat@gmail.com
License: BSD License
Keywords: django custom user auth model email without username
Platform: UNKNOWN
Classifier: Development Status :: 4 - Beta
Classifier: Environment :: Web Environment
Classifier: Framework :: Django
Classifier: Intended Audience :: Developers
Classifier: License :: OSI Approved :: BSD License
Classifier: Operating System :: OS Independent
Classifier: Programming Language :: Python
Classifier: Programming Language :: Python :: 2
Classifier: Programming Language :: Python :: 2.7
Classifier: Programming Language :: Python :: 3
Classifier: Programming Language :: Python :: 3.4
Classifier: Programming Language :: Python :: 3.5
Classifier: Topic :: Internet :: WWW/HTTP
Classifier: Topic :: Internet :: WWW/HTTP :: Dynamic Content
Requires-Dist: Django (>=1.5)
